audiolab/__init__.py
audiolab/cli.py
audiolab/pipe.py
audiolab/av/__init__.py
audiolab/av/codec.py
audiolab/av/container.py
audiolab/av/filter.py
audiolab/av/format.py
audiolab/av/frame.py
audiolab/av/graph.py
audiolab/av/layout.py
audiolab/av/lhotse.py
audiolab/av/typing.py
audiolab/av/utils.py
audiolab/av/templates/codec.txt
audiolab/av/templates/container.txt
audiolab/av/templates/filter.txt
audiolab/av/templates/format.txt
audiolab/av/templates/info.txt
audiolab/reader/__init__.py
audiolab/reader/info.py
audiolab/reader/reader.py
audiolab/reader/stream_reader.py
audiolab/reader/backend/__init__.py
audiolab/reader/backend/backend.py
audiolab/reader/backend/pyav.py
audiolab/reader/backend/soundfile.py
audiolab/reader/backend/wave.py
audiolab/writer/__init__.py
audiolab/writer/writer.py
audiolab/writer/backend/__init__.py
audiolab/writer/backend/backend.py
audiolab/writer/backend/pyav.py
audiolab/writer/backend/soundfile.py
audiolab/writer/backend/wave.py
audiolab-0.4.7.dist-info/licenses/LICENSE
audiolab-0.4.7.dist-info/METADATA
audiolab-0.4.7.dist-info/WHEEL
audiolab-0.4.7.dist-info/entry_points.txt
audiolab-0.4.7.dist-info/top_level.txt
audiolab-0.4.7.dist-info/RECORD
