Metadata-Version: 2.4
Name: audiolab
Version: 0.4.7
Summary: AudioLab
Author-email: Zhendong Peng <pzd17@tsinghua.org.cn>
License:                                  Apache License
Project-URL: Homepage, https://github.com/pengzhendong/audiolab
Project-URL: Documentation, https://github.com/pengzhendong/audiolab#readme
Project-URL: BugTracker, https://github.com/pengzhendong/audiolab/issues
Classifier: Programming Language :: Python :: 3
Classifier: Operating System :: OS Independent
Requires-Python: >=3.8
License-File: LICENSE
Requires-Dist: av
Requires-Dist: click
Requires-Dist: humanize
Requires-Dist: jinja2
Requires-Dist: smart_open
Requires-Dist: soundfile
Dynamic: license-file
